MANIFEST.in
README.rst
ez_setup.py
setup.py
htmq/__init__.py
htmq/html_parser.py
htmq/html_parser_debugger.py
htmq/html_query.py
htmq/stack.py
htmq/version.py
htmq.egg-info/PKG-INFO
htmq.egg-info/SOURCES.txt
htmq.egg-info/dependency_links.txt
htmq.egg-info/requires.txt
htmq.egg-info/top_level.txt