Metadata-Version: 1.1
Name: htmq
Version: 1.0.0
Summary: A fluent interface python library to query html.
Home-page: http://pypi.python.org/pypi/htmq/
Author: Amol Umrale
Author-email: babaiscool@gmail.com
License: UNKNOWN
Platform: UNKNOWN
Classifier: Development Status :: 4 - Beta
Classifier: Environment :: Console
Classifier: License :: OSI Approved :: MIT License
Classifier: Natural Language :: English
Classifier: Operating System :: Microsoft :: Windows
Classifier: Programming Language :: Python :: 3.4
